{"_id":{"$oid":"6475f4e70e0d6201abcd9d64"},"name":"KNXnet/IP","alias":["KNX","KNX/IP","Konnex"],"description":"Protocol for home and building automation systems.","keywords":["BMS","BAS","Building"],"port":"3671/udp","access":"Free","specs":[{"$oid":"6475f61f57e0c9ba88bdfef1"}],"security":"Optional, Security extensions available","nmap":[{"$oid":"6475f84318f4b06119555beb"}],"wireshark":[{"$oid":"6475f7c7302c382b339fb14f"}],"scapy":[{"$oid":"6475f7593d9386a5141bb24a"}],"pcap":"","cve":"","resources":[{"$oid":"6475fa933f9e3095afb60c59"},{"$oid":"6475fb026a5a4f44a0694588"}]}
